prowav/__init__.py
prowav/prowav.py
prowav/utils.py
prowav-0.6.dist-info/LICENSE
prowav-0.6.dist-info/METADATA
prowav-0.6.dist-info/WHEEL
prowav-0.6.dist-info/top_level.txt
prowav-0.6.dist-info/RECORD
