Metadata-Version: 2.1
Name: prowav
Version: 0.6
Summary: The package for preprocessing wave data
Home-page: https://github.com/wildgeece96/prowav
Author: Soh
Author-email: wildgeece96@gmail.com
License: MIT
Keywords: wave mfcc fft
Platform: UNKNOWN
Classifier: Programming Language :: Python :: 3.6
Requires-Dist: scipy (>=1.3.0)
Requires-Dist: numpy (>=1.16.1)
Requires-Dist: librosa (>=0.6.3)
Requires-Dist: wavio (>=0.0.4)
Requires-Dist: joblib
Requires-Dist: EMD-signal
Requires-Dist: tqdm
